pygoblet/__init__.py
pygoblet/optimizer.py
pygoblet/postprocessing.py
pygoblet/runners.py
pygoblet/cocopp_interface/__init__.py
pygoblet/cocopp_interface/interface.py
pygoblet/cocopp_interface/testbed.py
pygoblet/problems/__init__.py
pygoblet/problems/floris.py
pygoblet/problems/standard.py
pygoblet-0.1.0.dist-info/licenses/LICENCE.txt
pygoblet-0.1.0.dist-info/METADATA
pygoblet-0.1.0.dist-info/WHEEL
pygoblet-0.1.0.dist-info/top_level.txt
pygoblet-0.1.0.dist-info/RECORD
