Metadata-Version: 2.4
Name: pygoblet
Version: 0.1.0
Summary: A Python Global Optimization Benchmarking Library for Evaluation and Testing (pyGOBLET).
Author: Byron Selvage
Author-email: Weslley da Silva Pereira <weslley.dasilvapereira@nrel.gov>
License: BSD-3-Clause
Requires-Python: >=3.9
License-File: LICENCE.txt
Requires-Dist: numpy
Requires-Dist: matplotlib
Requires-Dist: array-api-compat
Requires-Dist: scipy
Requires-Dist: cocopp
Requires-Dist: pandas
Requires-Dist: floris
Dynamic: license-file
